axonserver/__init__.py
axonserver/axonserver.py
axonserver-1.0.1.dist-info/licenses/LICENSE
axonserver-1.0.1.dist-info/METADATA
axonserver-1.0.1.dist-info/WHEEL
axonserver-1.0.1.dist-info/entry_points.txt
axonserver-1.0.1.dist-info/top_level.txt
axonserver-1.0.1.dist-info/RECORD
