Metadata-Version: 2.4
Name: axonserver
Version: 1.0.1
Summary: axonserver desktop launcher
Requires-Python: >=3.8
License-File: LICENSE
Requires-Dist: pick
Requires-Dist: tqdm
Dynamic: license-file
